{
    "status": 0,
    "msg": "success",
    "data": {
        "dzwlInfoDataSum1": [
            {
              "title": "名称",
              "value": "D1290"
            },
            { "title": "有效时间段", "value": "2023-09-12" }
          ],
    
          "dzwlInfoDataSum2": [
            {
              "title": "人员闯入6次",
              "value": "北纬N34°42′24.46″ 东经E103°39′52.78″"
            },
            {
              "title": "人员闯入6次",
              "value": "北纬N34°42′24.46″ 东经E103°39′52.78″"
            },
            {
              "title": "人员闯入6次",
              "value": "北纬N34°42′24.46″ 东经E103°39′52.78″"
            },
            {
              "title": "人员闯入6次",
              "value": "北纬N34°42′24.46″ 东经E103°39′52.78″"
            },
            {
              "title": "人员闯入6次",
              "value": "北纬N34°42′24.46″ 东经E103°39′52.78″"
            },
            {
              "title": "人员闯入6次",
              "value": "北纬N34°42′24.46″ 东经E103°39′52.78″"
            }
          ]
    }
  }
  